{
    "AX": {
        "error": 0.004698765710207072, 
        "filter_outliers_dict": {
            "filter_outliers": true, 
            "iterations": 1, 
            "std_devs": 2
        }, 
        "fit": "average", 
        "value": 0.0751706949743165
    }, 
    "CDD": {
        "error": 2.763541225915984e-06, 
        "filter_outliers_dict": {
            "filter_outliers": true, 
            "iterations": 1, 
            "std_devs": 10
        }, 
        "fit": "average", 
        "value": 6.286016409021208e-06
    }, 
    "H1": {
        "error": 0.0035672704055970143, 
        "filter_outliers_dict": {
            "filter_outliers": true, 
            "iterations": 1, 
            "std_devs": 2
        }, 
        "fit": "average", 
        "value": -0.02329531191397405
    }, 
    "H2": {
        "error": 0.004899544659923979, 
        "filter_outliers_dict": {
            "filter_outliers": true, 
            "iterations": 1, 
            "std_devs": 2
        }, 
        "fit": "average", 
        "value": 0.07588288311004708
    }, 
    "L1": {
        "error": 0.0016110297811793221, 
        "filter_outliers_dict": {
            "filter_outliers": true, 
            "iterations": 1, 
            "std_devs": 2
        }, 
        "fit": "average", 
        "value": 0.004412816996267271
    }, 
    "L2": {
        "error": 0.004446946578814273, 
        "filter_outliers_dict": {
            "filter_outliers": true, 
            "iterations": 1, 
            "std_devs": 2
        }, 
        "fit": "average", 
        "value": 0.1347149937968532
    }
}