{
    "AX": {
        "error": 0.00480988218649325, 
        "filter_outliers_dict": {
            "filter_outliers": true, 
            "iterations": 1, 
            "std_devs": 2
        }, 
        "fit": "average", 
        "value": -0.04039240056484803
    }, 
    "CDD": {
        "error": 4.551614756389479e-06, 
        "filter_outliers_dict": {
            "filter_outliers": true, 
            "iterations": 1, 
            "std_devs": 10
        }, 
        "fit": "average", 
        "value": 1.5982891406285392e-05
    }, 
    "H1": {
        "error": 0.0034907949134830103, 
        "filter_outliers_dict": {
            "filter_outliers": true, 
            "iterations": 1, 
            "std_devs": 2
        }, 
        "fit": "average", 
        "value": 0.0008797879974123487
    }, 
    "H2": {
        "error": 0.005660558425294284, 
        "filter_outliers_dict": {
            "filter_outliers": true, 
            "iterations": 1, 
            "std_devs": 2
        }, 
        "fit": "average", 
        "value": -0.1847102711308041
    }, 
    "L1": {
        "error": 0.0019506192646363326, 
        "filter_outliers_dict": {
            "filter_outliers": true, 
            "iterations": 1, 
            "std_devs": 2
        }, 
        "fit": "average", 
        "value": -0.01608902727357964
    }, 
    "L2": {
        "error": 0.0042726819648010875, 
        "filter_outliers_dict": {
            "filter_outliers": true, 
            "iterations": 1, 
            "std_devs": 2
        }, 
        "fit": "average", 
        "value": -0.018802440615055618
    }
}