{
    "AX": {
        "error": 0.004385514829165638, 
        "filter_outliers": true, 
        "filter_outliers_dict": {
            "filter_outliers": true, 
            "iterations": 1, 
            "std_devs": 2
        }, 
        "fit": "Average", 
        "fn": 114, 
        "include_baseline_error": false, 
        "iterations": 1, 
        "n": 120, 
        "std_devs": 2, 
        "value": -0.02109817009043406
    }, 
    "CDD": {
        "error": 4.938124827103088e-06, 
        "filter_outliers_dict": {
            "filter_outliers": true, 
            "iterations": 1, 
            "std_devs": 10
        }, 
        "fit": "average", 
        "value": 1.975249928763575e-05
    }, 
    "H1": {
        "error": 0.003559680110484442, 
        "filter_outliers": true, 
        "filter_outliers_dict": {
            "filter_outliers": true, 
            "iterations": 1, 
            "std_devs": 2
        }, 
        "fit": "Average", 
        "fn": 115, 
        "include_baseline_error": false, 
        "iterations": 1, 
        "n": 120, 
        "std_devs": 2, 
        "value": -0.0338888998163621
    }, 
    "H2": {
        "error": 0.0050232599036661284, 
        "filter_outliers": true, 
        "filter_outliers_dict": {
            "filter_outliers": true, 
            "iterations": 1, 
            "std_devs": 2
        }, 
        "fit": "Average", 
        "fn": 115, 
        "include_baseline_error": false, 
        "iterations": 1, 
        "n": 120, 
        "std_devs": 2, 
        "value": -0.15324475723116293
    }, 
    "L1": {
        "error": 0.0017184903270666227, 
        "filter_outliers": true, 
        "filter_outliers_dict": {
            "filter_outliers": true, 
            "iterations": 1, 
            "std_devs": 2
        }, 
        "fit": "Average", 
        "fn": 116, 
        "include_baseline_error": false, 
        "iterations": 1, 
        "n": 120, 
        "std_devs": 2, 
        "value": -0.013547281304109392
    }, 
    "L2": {
        "error": 0.004699719486903206, 
        "filter_outliers_dict": {
            "filter_outliers": true, 
            "iterations": 1, 
            "std_devs": 2
        }, 
        "fit": "average", 
        "value": -0.013802594979392884
    }
}