{
    "Ar36": {
        "error": 0.00024266910393861525, 
        "filter_outliers": true, 
        "filter_outliers_dict": {
            "filter_outliers": true, 
            "iterations": 1, 
            "std_devs": 2
        }, 
        "fit": "Parabolic", 
        "fn": 382, 
        "include_baseline_error": false, 
        "iterations": 1, 
        "n": 400, 
        "std_devs": 2, 
        "value": 0.011689565342775668
    }, 
    "Ar37": {
        "error": 0.004995489029167311, 
        "filter_outliers": true, 
        "filter_outliers_dict": {
            "filter_outliers": true, 
            "iterations": 1, 
            "std_devs": 2
        }, 
        "fit": "Linear", 
        "fn": 382, 
        "include_baseline_error": false, 
        "iterations": 1, 
        "n": 400, 
        "std_devs": 2, 
        "value": 0.015086920302670951
    }, 
    "Ar38": {
        "error": 0.0019245995604189044, 
        "filter_outliers": true, 
        "filter_outliers_dict": {
            "filter_outliers": true, 
            "iterations": 1, 
            "std_devs": 2
        }, 
        "fit": "Linear", 
        "fn": 382, 
        "include_baseline_error": false, 
        "iterations": 1, 
        "n": 400, 
        "std_devs": 2, 
        "value": 0.011087064156670743
    }, 
    "Ar39": {
        "error": 0.008198291739071833, 
        "filter_outliers": true, 
        "filter_outliers_dict": {
            "filter_outliers": true, 
            "iterations": 1, 
            "std_devs": 2
        }, 
        "fit": "Parabolic", 
        "fn": 377, 
        "include_baseline_error": false, 
        "iterations": 1, 
        "n": 400, 
        "std_devs": 2, 
        "value": 0.08478175354842825
    }, 
    "Ar40": {
        "error": 0.0068884558161835426, 
        "filter_outliers": true, 
        "filter_outliers_dict": {
            "filter_outliers": true, 
            "iterations": 1, 
            "std_devs": 2
        }, 
        "fit": "Parabolic", 
        "fn": 380, 
        "include_baseline_error": false, 
        "iterations": 1, 
        "n": 400, 
        "std_devs": 2, 
        "value": 0.6857000018834186
    }, 
    "Ar41": {
        "error": 0.0028869027792114677, 
        "filter_outliers": true, 
        "filter_outliers_dict": {
            "filter_outliers": true, 
            "iterations": 1, 
            "std_devs": 2
        }, 
        "fit": "Average", 
        "fn": 385, 
        "include_baseline_error": false, 
        "iterations": 1, 
        "n": 400, 
        "std_devs": 2, 
        "value": -0.015408352196693583
    }, 
    "reviewed": true
}