{
    "Ar36": {
        "error": 0.00017241582841957513,
        "filter_outliers_dict": {
            "filter_outliers": true,
            "iterations": 1,
            "std_devs": 2
        },
        "fit": "Parabolic",
        "fn": 571,
        "include_baseline_error": false,
        "n": 600,
        "reviewed": true,
        "value": 0.009331277866100354
    },
    "Ar37": {
        "error": 0.003911576045905188,
        "filter_outliers_dict": {
            "filter_outliers": true,
            "iterations": 1,
            "std_devs": 2
        },
        "fit": "Linear",
        "fn": 571,
        "include_baseline_error": false,
        "n": 600,
        "reviewed": true,
        "value": 0.010609998752552557
    },
    "Ar38": {
        "error": 0.00165782106989403,
        "filter_outliers_dict": {
            "filter_outliers": true,
            "iterations": 1,
            "std_devs": 2
        },
        "fit": "Linear",
        "fn": 568,
        "include_baseline_error": false,
        "n": 600,
        "reviewed": true,
        "value": -0.020329499740014356
    },
    "Ar39": {
        "error": 0.007133629222359623,
        "filter_outliers_dict": {
            "filter_outliers": true,
            "iterations": 1,
            "std_devs": 2
        },
        "fit": "Parabolic",
        "fn": 574,
        "include_baseline_error": false,
        "n": 600,
        "reviewed": true,
        "value": 0.0037528161232040433
    },
    "Ar40": {
        "error": 0.0056110078450771535,
        "filter_outliers_dict": {
            "filter_outliers": true,
            "iterations": 1,
            "std_devs": 2
        },
        "fit": "Parabolic",
        "fn": 568,
        "include_baseline_error": false,
        "n": 600,
        "reviewed": true,
        "value": 1.183914802455989
    },
    "Ar41": {
        "error": 0.004004175271741062,
        "filter_outliers_dict": {
            "filter_outliers": true,
            "iterations": 1,
            "std_devs": 2
        },
        "fit": "linear",
        "value": -0.14919861530682246
    }
}