{
    "Ar36": {
        "error": 0.0002613037417698353,
        "filter_outliers_dict": {
            "filter_outliers": true,
            "iterations": 1,
            "std_devs": 2
        },
        "fit": "Parabolic",
        "fn": 576,
        "include_baseline_error": false,
        "n": 600,
        "reviewed": true,
        "value": 0.027235130633782946
    },
    "Ar37": {
        "error": 0.003931748241184805,
        "filter_outliers_dict": {
            "filter_outliers": true,
            "iterations": 1,
            "std_devs": 2
        },
        "fit": "Linear",
        "fn": 576,
        "include_baseline_error": false,
        "n": 600,
        "reviewed": true,
        "value": 0.005804724413014439
    },
    "Ar38": {
        "error": 0.0017598894648564016,
        "filter_outliers_dict": {
            "filter_outliers": true,
            "iterations": 1,
            "std_devs": 2
        },
        "fit": "Linear",
        "fn": 575,
        "include_baseline_error": false,
        "n": 600,
        "reviewed": true,
        "value": -0.008713158049688523
    },
    "Ar39": {
        "error": 0.0067302227934130186,
        "filter_outliers_dict": {
            "filter_outliers": true,
            "iterations": 1,
            "std_devs": 2
        },
        "fit": "Parabolic",
        "fn": 573,
        "include_baseline_error": false,
        "n": 600,
        "reviewed": true,
        "value": 0.22281284017813144
    },
    "Ar40": {
        "error": 0.006043029264390958,
        "filter_outliers_dict": {
            "filter_outliers": true,
            "iterations": 1,
            "std_devs": 2
        },
        "fit": "Parabolic",
        "fn": 574,
        "include_baseline_error": false,
        "n": 600,
        "reviewed": true,
        "value": 8.935425921118366
    },
    "Ar41": {
        "error": 0.004948433946051977,
        "filter_outliers_dict": {
            "filter_outliers": true,
            "iterations": 1,
            "std_devs": 2
        },
        "fit": "linear",
        "value": -0.16643781358887835
    }
}