{
    "Ar36": {
        "error": 0.00023633793707208294, 
        "filter_outliers": true, 
        "filter_outliers_dict": {
            "filter_outliers": true, 
            "iterations": 1, 
            "std_devs": 2
        }, 
        "fit": "Parabolic", 
        "fn": 382, 
        "include_baseline_error": false, 
        "iterations": 1, 
        "n": 400, 
        "std_devs": 2, 
        "value": 0.010403052100945054
    }, 
    "Ar37": {
        "error": 0.005054510557703108, 
        "filter_outliers": true, 
        "filter_outliers_dict": {
            "filter_outliers": true, 
            "iterations": 1, 
            "std_devs": 2
        }, 
        "fit": "Linear", 
        "fn": 382, 
        "include_baseline_error": false, 
        "iterations": 1, 
        "n": 400, 
        "std_devs": 2, 
        "value": 0.01717646037131725
    }, 
    "Ar38": {
        "error": 0.0021472156737225787, 
        "filter_outliers": true, 
        "filter_outliers_dict": {
            "filter_outliers": true, 
            "iterations": 1, 
            "std_devs": 2
        }, 
        "fit": "Linear", 
        "fn": 382, 
        "include_baseline_error": false, 
        "iterations": 1, 
        "n": 400, 
        "std_devs": 2, 
        "value": 0.0012933306360919804
    }, 
    "Ar39": {
        "error": 0.008254988661009884, 
        "filter_outliers": true, 
        "filter_outliers_dict": {
            "filter_outliers": true, 
            "iterations": 1, 
            "std_devs": 2
        }, 
        "fit": "Parabolic", 
        "fn": 386, 
        "include_baseline_error": false, 
        "iterations": 1, 
        "n": 400, 
        "std_devs": 2, 
        "value": 0.05134208178341289
    }, 
    "Ar40": {
        "error": 0.0071832851660479, 
        "filter_outliers": true, 
        "filter_outliers_dict": {
            "filter_outliers": true, 
            "iterations": 1, 
            "std_devs": 2
        }, 
        "fit": "Parabolic", 
        "fn": 381, 
        "include_baseline_error": false, 
        "iterations": 1, 
        "n": 400, 
        "std_devs": 2, 
        "value": 0.5782216724696266
    }, 
    "Ar41": {
        "error": 0.0063216756033359495, 
        "filter_outliers_dict": {
            "filter_outliers": true, 
            "iterations": 1, 
            "std_devs": 2
        }, 
        "fit": "linear", 
        "value": -0.10462337264119087
    }, 
    "reviewed": true
}