{
    "Ar36": {
        "error": 0.00024648485054047127, 
        "filter_outliers": true, 
        "filter_outliers_dict": {
            "filter_outliers": true, 
            "iterations": 1, 
            "std_devs": 2
        }, 
        "fit": "Parabolic", 
        "fn": 382, 
        "include_baseline_error": false, 
        "iterations": 1, 
        "n": 400, 
        "std_devs": 2, 
        "value": 0.01175781635746323
    }, 
    "Ar37": {
        "error": 0.004912816215520521, 
        "filter_outliers": true, 
        "filter_outliers_dict": {
            "filter_outliers": true, 
            "iterations": 1, 
            "std_devs": 2
        }, 
        "fit": "Linear", 
        "fn": 379, 
        "include_baseline_error": false, 
        "iterations": 1, 
        "n": 400, 
        "std_devs": 2, 
        "value": 0.012366132132825575
    }, 
    "Ar38": {
        "error": 0.0020751109075581734, 
        "filter_outliers": true, 
        "filter_outliers_dict": {
            "filter_outliers": true, 
            "iterations": 1, 
            "std_devs": 2
        }, 
        "fit": "Linear", 
        "fn": 377, 
        "include_baseline_error": false, 
        "iterations": 1, 
        "n": 400, 
        "std_devs": 2, 
        "value": 0.0014149485274475636
    }, 
    "Ar39": {
        "error": 0.008108094235513747, 
        "filter_outliers": true, 
        "filter_outliers_dict": {
            "filter_outliers": true, 
            "iterations": 1, 
            "std_devs": 2
        }, 
        "fit": "Parabolic", 
        "fn": 378, 
        "include_baseline_error": false, 
        "iterations": 1, 
        "n": 400, 
        "std_devs": 2, 
        "value": 0.05227840262459997
    }, 
    "Ar40": {
        "error": 0.007060007491615581, 
        "filter_outliers": true, 
        "filter_outliers_dict": {
            "filter_outliers": true, 
            "iterations": 1, 
            "std_devs": 2
        }, 
        "fit": "Parabolic", 
        "fn": 381, 
        "include_baseline_error": false, 
        "iterations": 1, 
        "n": 400, 
        "std_devs": 2, 
        "value": 0.4259966508688024
    }, 
    "Ar41": {
        "error": 0.003048115522385496, 
        "filter_outliers": true, 
        "filter_outliers_dict": {
            "filter_outliers": true, 
            "iterations": 1, 
            "std_devs": 2
        }, 
        "fit": "Average", 
        "fn": 385, 
        "include_baseline_error": false, 
        "iterations": 1, 
        "n": 400, 
        "std_devs": 2, 
        "value": -0.07375246003450064
    }, 
    "reviewed": true
}